project_1.srcs/sources_1/new/matrix_decoder.sv
`timescale 1ns / 1ps
//////////////////////////////////////////////////////////////////////////////////
// Company: 
// Engineer: 
// 
// Create Date: 06/29/2026 01:30:21 PM
// Design Name: 
// Module Name: matrix_decoder
// Project Name: 
// Target Devices: 
// Tool Versions: 
// Description: 
// 
// Dependencies: 
// 
// Revision:
// Revision 0.01 - File Created
// Additional Comments:
// 
//////////////////////////////////////////////////////////////////////////////////


module matrix_decoder(
        output logic JC1, JC2, JC3, JC4, 
        input logic JC7, JC8, JC9, JC10,
        input logic clk,
  		output logic [3:0] sel_number,
  		//output logic [1:0] row_no,
  		//output logic [1:0] col_no,
  		input logic nReset,
  		//output logic col_on,
  		output logic ignore_input
    );
    
   
   // Read from columns, write to rows
    
    
    logic [1:0] row_no;
    logic [1:0] col_no;
    
  		always_ff @(posedge clk or negedge nReset) begin
       
          
           // Setting iteration
        if (!nReset) begin  
          row_no <= 2'b00;
          col_no <= 2'b00;
        end
        else begin
          if (col_no == 2'b11) row_no <= row_no + 1;
          col_no <= col_no + 1;
        end
          
          
       
    end
    
    // Setting which row to write
    always_comb begin
        case (row_no)
            2'b00 : {JC1, JC2, JC3, JC4} = 4'b1000;
            2'b01 : {JC1, JC2, JC3, JC4} = 4'b0100;
            2'b10 : {JC1, JC2, JC3, JC4} = 4'b0010;
            2'b11 : {JC1, JC2, JC3, JC4} = 4'b0001;
        endcase
     end
     
  	// Setting from which column to read
  	
  	logic col_on;
  
  	always_comb begin
      case (col_no)
        2'b00 : col_on = JC7;
        2'b01 : col_on = JC8;
        2'b10 : col_on = JC9;
        2'b11 : col_on = JC10;
      endcase
    end
  
  
  // Parsing out to sel_number (TO CHANGE SO IT DEPENDS FROM COLUMN INPUT)]
  always_comb begin
    if (col_on) // Flag to ignore output from decoder as no input is appearing from columns
      begin
        if ((col_no != 2'b11) & (row_no != 2'b11)) sel_number <= ({2'b00, row_no} << 1) + (row_no + 1 + col_no); // Digits 
        else if (col_no == 2'b11) sel_number <= {2'b00, row_no} + 4'hC; // Last Column Hex Digits
    	else if (col_no[0] == 1'b0) sel_number <= ({2'b00 , col_no} >> 1) + 4'hA; // A and B
        else sel_number <= 4'b0000; // 0
        
        ignore_input <= 0;
      end 
    else ignore_input <= 1;
  
  end
        
        
     
endmodule

project_1.srcs/sim_1/new/matrix_decoder_tb.sv
`timescale 1ns / 1ps
//////////////////////////////////////////////////////////////////////////////////
// Company: 
// Engineer: 
// 
// Create Date: 06/29/2026 09:37:03 PM
// Design Name: 
// Module Name: matrix_decoder_tb
// Project Name: 
// Target Devices: 
// Tool Versions: 
// Description: 
// 
// Dependencies: 
// 
// Revision:
// Revision 0.01 - File Created
// Additional Comments:
// 
//////////////////////////////////////////////////////////////////////////////////


module matrix_decoder_tb;

// Commented out signals are internal to see on observation  

logic JC1, JC2, JC3, JC4; // JC1 is row 0 
logic JC7, JC8, JC9, JC10; // JC7 is col 0;
logic clk;
logic [3:0] sel_number;
//logic [1:0] row_no;
//logic [1:0] col_no;
logic nReset;
//logic col_on;
logic ignore_input;

matrix_decoder md0 (.*);

always #2ns clk <= ~clk;
  

// One thing this testbench doesn't account for is the fact that it will alternate between on and off for scanning rows

initial begin
  
    $dumpfile("dump.vcd");
  	$dumpvars(1);
    
    // Ensuring 0 is yielded
    JC7 = 1; JC8 = 0; JC9 = 0; JC10 = 0; nReset = 1;
        
    clk = 0;
  
  	#1ns nReset = 0;
  	#1ns nReset = 1;
    
    #62ns JC7 = 0; JC8 = 1;
    
    #64ns JC8 = 0; JC9 = 1;
    
    #64ns JC9 = 0; JC10 = 1;
    
    #64ns JC7 = 1;

end

endmodule

project_1.sim/sim_1/behav/xsim/dump.vcd
$date
   Wed Jul  1 20:29:42 2026
$end

$version
  2025.2
  $dumpfile ("dump.vcd") 
$end

$timescale
  1ps
$end

$scope module matrix_decoder_tb $end
$var reg 1 ! JC1 $end
$var reg 1 " JC2 $end
$var reg 1 # JC3 $end
$var reg 1 $ JC4 $end
$var reg 1 % JC7 $end
$var reg 1 & JC8 $end
$var reg 1 ' JC9 $end
$var reg 1 ( JC10 $end
$var reg 1 ) clk $end
$var reg 4 * sel_number [3:0] $end
$var reg 1 + nReset $end
$var reg 1 , ignore_input $end
$upscope $end
$scope module glbl $end
$upscope $end
$enddefinitions $end

#0
$dumpvars
x!
x"
x#
x$
1%
0&
0'
0(
0)
bx *
1+
1,
$end

#1000
1!
0"
0#
0$
b1 *
0+
0,

#2000
1)
1+
1,

#4000
0)

#6000
1)

#8000
0)

#10000
1)

#12000
0)

#14000
0!
1"
1)
b100 *
0,

#16000
0)

#18000
1)
1,

#20000
0)

#22000
1)

#24000
0)

#26000
1)

#28000
0)

#30000
0"
1#
1)
b111 *
0,

#32000
0)

#34000
1)
1,

#36000
0)

#38000
1)

#40000
0)

#42000
1)

#44000
0)

#46000
0#
1$
1)
b1010 *
0,

#48000
0)

#50000
1)
1,

#52000
0)

#54000
1)

#56000
0)

#58000
1)

#60000
0)

#62000
1!
0$
1)
b1 *
0,

#64000
0%
1&
0)
1,

#66000
1)
b10 *
0,

#68000
0)

#70000
1)
1,

#72000
0)

#74000
1)

#76000
0)

#78000
0!
1"
1)

#80000
0)

#82000
1)
b101 *
0,

#84000
0)

#86000
1)
1,

#88000
0)

#90000
1)

#92000
0)

#94000
0"
1#
1)

#96000
0)

#98000
1)
b1000 *
0,

#100000
0)

#102000
1)
1,

#104000
0)

#106000
1)

#108000
0)

#110000
0#
1$
1)

#112000
0)

#114000
1)
b0 *
0,

#116000
0)

#118000
1)
1,

#120000
0)

#122000
1)

#124000
0)

#126000
1!
0$
1)

#128000
0&
1'
0)

#130000
1)

#132000
0)

#134000
1)
b11 *
0,

#136000
0)

#138000
1)
1,

#140000
0)

#142000
0!
1"
1)

#144000
0)

#146000
1)

#148000
0)

#150000
1)
b110 *
0,

#152000
0)

#154000
1)
1,

#156000
0)

#158000
0"
1#
1)

#160000
0)

#162000
1)

#164000
0)

#166000
1)
b1001 *
0,

#168000
0)

#170000
1)
1,

#172000
0)

#174000
0#
1$
1)

#176000
0)

#178000
1)

#180000
0)

#182000
1)
b1011 *
0,

#184000
0)

#186000
1)
1,

#188000
0)

#190000
1!
0$
1)

#192000
0'
1(
0)

#194000
1)

#196000
0)

#198000
1)

#200000
0)

#202000
1)
b1100 *
0,

#204000
0)

#206000
0!
1"
1)
b100 *
1,

#208000
0)

#210000
1)

#212000
0)

#214000
1)

#216000
0)

#218000
1)
b1101 *
0,

#220000
0)

#222000
0"
1#
1)
b111 *
1,

#224000
0)

#226000
1)

#228000
0)

#230000
1)

#232000
0)

#234000
1)
b1110 *
0,

#236000
0)

#238000
0#
1$
1)
b1010 *
1,

#240000
0)

#242000
1)

#244000
0)

#246000
1)

#248000
0)

#250000
1)
b1111 *
0,

#252000
0)

#254000
1!
0$
1)
b1 *
1,

#256000
1%
0)
0,

#258000
1)
1,

#260000
0)

#262000
1)

#264000
0)

#266000
1)
b1100 *
0,

#268000
0)

#270000
0!
1"
1)
b100 *

#272000
0)

#274000
1)
1,

#276000
0)

#278000
1)

#280000
0)

#282000
1)
b1101 *
0,

#284000
0)

#286000
0"
1#
1)
b111 *

#288000
0)

#290000
1)
1,

#292000
0)

#294000
1)

#296000
0)

#298000
1)
b1110 *
0,

#300000
0)

#302000
0#
1$
1)
b1010 *

#304000
0)

#306000
1)
1,

#308000
0)

#310000
1)

#312000
0)

#314000
1)
b1111 *
0,

#316000
0)

#318000
1!
0$
1)
b1 *

#320000
0)

#322000
1)
1,

#324000
0)

#326000
1)

#328000
0)

#330000
1)
b1100 *
0,

#332000
0)

#334000
0!
1"
1)
b100 *

#336000
0)

#338000
1)
1,

#340000
0)

#342000
1)

#344000
0)

#346000
1)
b1101 *
0,

#348000
0)

#350000
0"
1#
1)
b111 *

#352000
0)

#354000
1)
1,

#356000
0)

#358000
1)

#360000
0)

#362000
1)
b1110 *
0,

#364000
0)

#366000
0#
1$
1)
b1010 *

#368000
0)

#370000
1)
1,

#372000
0)

#374000
1)

#376000
0)

#378000
1)
b1111 *
0,

#380000
0)

#382000
1!
0$
1)
b1 *

#384000
0)

#386000
1)
1,

#388000
0)

#390000
1)

#392000
0)

#394000
1)
b1100 *
0,

#396000
0)

#398000
0!
1"
1)
b100 *

#400000
0)

#402000
1)
1,

#404000
0)

#406000
1)

#408000
0)

#410000
1)
b1101 *
0,

#412000
0)

#414000
0"
1#
1)
b111 *

#416000
0)

#418000
1)
1,

#420000
0)

#422000
1)

#424000
0)

#426000
1)
b1110 *
0,

#428000
0)

#430000
0#
1$
1)
b1010 *

#432000
0)

#434000
1)
1,

#436000
0)

#438000
1)

#440000
0)

#442000
1)
b1111 *
0,

#444000
0)

#446000
1!
0$
1)
b1 *

#448000
0)

#450000
1)
1,

#452000
0)

#454000
1)

#456000
0)

#458000
1)
b1100 *
0,

#460000
0)

#462000
0!
1"
1)
b100 *

#464000
0)

#466000
1)
1,

#468000
0)

#470000
1)

#472000
0)

#474000
1)
b1101 *
0,

#476000
0)

#478000
0"
1#
1)
b111 *

#480000
0)

#482000
1)
1,

#484000
0)

#486000
1)

#488000
0)

#490000
1)
b1110 *
0,

#492000
0)

#494000
0#
1$
1)
b1010 *

#496000
0)

#498000
1)
1,

#500000
0)

#502000
1)

#504000
0)

#506000
1)
b1111 *
0,

#508000
0)

#510000
1!
0$
1)
b1 *

#512000
0)

#514000
1)
1,

#516000
0)

#518000
1)

#520000
0)

#522000
1)
b1100 *
0,

#524000
0)

#526000
0!
1"
1)
b100 *

#528000
0)

#530000
1)
1,

#532000
0)

#534000
1)

#536000
0)

#538000
1)
b1101 *
0,

#540000
0)

#542000
0"
1#
1)
b111 *

#544000
0)

#546000
1)
1,

#548000
0)

#550000
1)

#552000
0)

#554000
1)
b1110 *
0,

#556000
0)

#558000
0#
1$
1)
b1010 *

#560000
0)

#562000
1)
1,

#564000
0)

#566000
1)

#568000
0)

#570000
1)
b1111 *
0,

#572000
0)

#574000
1!
0$
1)
b1 *

#576000
0)

#578000
1)
1,

#580000
0)

#582000
1)

#584000
0)

#586000
1)
b1100 *
0,

#588000
0)

#590000
0!
1"
1)
b100 *

#592000
0)

#594000
1)
1,

#596000
0)

#598000
1)

#600000
0)

#602000
1)
b1101 *
0,

#604000
0)

#606000
0"
1#
1)
b111 *

#608000
0)

#610000
1)
1,

#612000
0)

#614000
1)

#616000
0)

#618000
1)
b1110 *
0,

#620000
0)

#622000
0#
1$
1)
b1010 *

#624000
0)

#626000
1)
1,

#628000
0)

#630000
1)

#632000
0)

#634000
1)
b1111 *
0,

#636000
0)

#638000
1!
0$
1)
b1 *

#640000
0)

#642000
1)
1,

#644000
0)

#646000
1)

#648000
0)

#650000
1)
b1100 *
0,

#652000
0)

#654000
0!
1"
1)
b100 *

#656000
0)

#658000
1)
1,

#660000
0)

#662000
1)

#664000
0)

#666000
1)
b1101 *
0,

#668000
0)

#670000
0"
1#
1)
b111 *

#672000
0)

#674000
1)
1,

#676000
0)

#678000
1)

#680000
0)

#682000
1)
b1110 *
0,

#684000
0)

#686000
0#
1$
1)
b1010 *

#688000
0)

#690000
1)
1,

#692000
0)

#694000
1)

#696000
0)

#698000
1)
b1111 *
0,

#700000
0)

#702000
1!
0$
1)
b1 *

#704000
0)

#706000
1)
1,

#708000
0)

#710000
1)

#712000
0)

#714000
1)
b1100 *
0,

#716000
0)

#718000
0!
1"
1)
b100 *

#720000
0)

#722000
1)
1,

#724000
0)

#726000
1)

#728000
0)

#730000
1)
b1101 *
0,

#732000
0)

#734000
0"
1#
1)
b111 *

#736000
0)

#738000
1)
1,

#740000
0)

#742000
1)

#744000
0)

#746000
1)
b1110 *
0,

#748000
0)

#750000
0#
1$
1)
b1010 *

#752000
0)

#754000
1)
1,

#756000
0)

#758000
1)

#760000
0)

#762000
1)
b1111 *
0,

#764000
0)

#766000
1!
0$
1)
b1 *

#768000
0)

#770000
1)
1,

#772000
0)

#774000
1)

#776000
0)

#778000
1)
b1100 *
0,

#780000
0)

#782000
0!
1"
1)
b100 *

#784000
0)

#786000
1)
1,

#788000
0)

#790000
1)

#792000
0)

#794000
1)
b1101 *
0,

#796000
0)

#798000
0"
1#
1)
b111 *

#800000
0)

#802000
1)
1,

#804000
0)

#806000
1)

#808000
0)

#810000
1)
b1110 *
0,

#812000
0)

#814000
0#
1$
1)
b1010 *

#816000
0)

#818000
1)
1,

#820000
0)

#822000
1)

#824000
0)

#826000
1)
b1111 *
0,

#828000
0)

#830000
1!
0$
1)
b1 *

#832000
0)

#834000
1)
1,

#836000
0)

#838000
1)

#840000
0)

#842000
1)
b1100 *
0,

#844000
0)

#846000
0!
1"
1)
b100 *

#848000
0)

#850000
1)
1,

#852000
0)

#854000
1)

#856000
0)

#858000
1)
b1101 *
0,

#860000
0)

#862000
0"
1#
1)
b111 *

#864000
0)

#866000
1)
1,

#868000
0)

#870000
1)

#872000
0)

#874000
1)
b1110 *
0,

#876000
0)

#878000
0#
1$
1)
b1010 *

#880000
0)

#882000
1)
1,

#884000
0)

#886000
1)

#888000
0)

#890000
1)
b1111 *
0,

#892000
0)

#894000
1!
0$
1)
b1 *

#896000
0)

#898000
1)
1,

#900000
0)

#902000
1)

#904000
0)

#906000
1)
b1100 *
0,

#908000
0)

#910000
0!
1"
1)
b100 *

#912000
0)

#914000
1)
1,

#916000
0)

#918000
1)

#920000
0)

#922000
1)
b1101 *
0,

#924000
0)

#926000
0"
1#
1)
b111 *

#928000
0)

#930000
1)
1,

#932000
0)

#934000
1)

#936000
0)

#938000
1)
b1110 *
0,

#940000
0)

#942000
0#
1$
1)
b1010 *

#944000
0)

#946000
1)
1,

#948000
0)

#950000
1)

#952000
0)

#954000
1)
b1111 *
0,

#956000
0)

#958000
1!
0$
1)
b1 *

#960000
0)

#962000
1)
1,

#964000
0)

#966000
1)

#968000
0)

#970000
1)
b1100 *
0,

#972000
0)

#974000
0!
1"
1)
b100 *

#976000
0)

#978000
1)
1,

#980000
0)

#982000
1)

#984000
0)

#986000
1)
b1101 *
0,

#988000
0)

#990000
0"
1#
1)
b111 *

#992000
0)

#994000
1)
1,

